winregal/__init__.py
winregal/winregal.py
winregal-1.0.1.dist-info/DESCRIPTION.rst
winregal-1.0.1.dist-info/LICENSE.txt
winregal-1.0.1.dist-info/METADATA
winregal-1.0.1.dist-info/RECORD
winregal-1.0.1.dist-info/WHEEL
winregal-1.0.1.dist-info/metadata.json
winregal-1.0.1.dist-info/top_level.txt
